tradologics/__init__.py
tradologics/backtest.py
tradologics/helpers.py
tradologics/requests.py
tradologics/sandbox.py
tradologics/server.py
tradologics-0.0.22.dist-info/LICENSE.txt
tradologics-0.0.22.dist-info/METADATA
tradologics-0.0.22.dist-info/WHEEL
tradologics-0.0.22.dist-info/top_level.txt
tradologics-0.0.22.dist-info/RECORD
