Metadata-Version: 2.1
Name: tradologics
Version: 0.0.22
Summary: Tradologics SDK
Home-page: https://tradologics.com
Author: Tradologics, Inc.
Author-email: opensource@tradologics.com
License: Apache 2.0
Keywords: tradologics,tradologics.com
Platform: any
Classifier: License :: OSI Approved :: Apache Software License
Classifier: Development Status :: 4 - Beta
Classifier: Operating System :: OS Independent
Classifier: Intended Audience :: Developers
Classifier: Topic :: Office/Business :: Financial
Classifier: Topic :: Office/Business :: Financial :: Investment
Classifier: Topic :: Software Development :: Libraries
Classifier: Topic :: Software Development :: Libraries :: Python Modules
Classifier: Programming Language :: Python :: 3.6
Classifier: Programming Language :: Python :: 3.7
Classifier: Programming Language :: Python :: 3.8
Classifier: Programming Language :: Python :: 3.9
License-File: LICENSE.txt
Requires-Dist: requests (==2.24.0)
Requires-Dist: pyzmq (==19.0.2)
Requires-Dist: pandas (>=0.24.2)
Requires-Dist: Flask (==2.0.2)
